{
    "title": "lektion 26",
    "vocab": [
        {
            "word": "aparat",
            "translation": "Kamera"
        },
        {
            "word": "lekcje tańca",
            "translation": "Tanzstunden"
        },
        {
            "word": "wysoki",
            "translation": "hoch"
        },
        {
            "word": "market",
            "translation": "Supermarkt"
        },
        {
            "word": "puzzle",
            "translation": "Puzzle"
        },
        {
            "word": "nigdy",
            "translation": "nie"
        },
        {
            "word": "szybki",
            "translation": "schnell"
        },
        {
            "word": "kort tenisowy",
            "translation": "Tennisplatz"
        },
        {
            "word": "ręcznik",
            "translation": "Handtuch"
        },
        {
            "word": "niebo",
            "translation": "Himmel"
        },
        {
            "word": "brudny",
            "translation": "schmutzig"
        },
        {
            "word": "serial",
            "translation": "Serie"
        },
        {
            "word": "nie",
            "translation": "nicht"
        },
        {
            "word": "miękki",
            "translation": "weich"
        },
        {
            "word": "galeria sztuki",
            "translation": "Kunstgalerie"
        },
        {
            "word": "śpiewa",
            "translation": "singt"
        },
        {
            "word": "my",
            "translation": "wir"
        },
        {
            "word": "rękawiczki",
            "translation": "Handschuhe"
        },
        {
            "word": "prawko",
            "translation": "Führerschein"
        },
        {
            "word": "luty",
            "translation": "Februar"
        }
    ]
}