{
    "title": "Lektion 7",
    "vocab": [
        {
            "word": "pays",
            "translation": "Land"
        },
        {
            "word": "père",
            "translation": "Vater"
        },
        {
            "word": "personne",
            "translation": "Person"
        },
        {
            "word": "petit",
            "translation": "klein"
        },
        {
            "word": "peu",
            "translation": "wenig"
        },
        {
            "word": "peur",
            "translation": "Angst"
        },
        {
            "word": "plaire",
            "translation": "gefallen"
        },
        {
            "word": "plein",
            "translation": "voll"
        },
        {
            "word": "plus",
            "translation": "mehr"
        },
        {
            "word": "pouvoir",
            "translation": "können"
        },
        {
            "word": "prendre",
            "translation": "nehmen"
        },
        {
            "word": "près",
            "translation": "nahe"
        },
        {
            "word": "prier",
            "translation": "bitten"
        },
        {
            "word": "professeur",
            "translation": "Lehrer"
        },
        {
            "word": "propre",
            "translation": "sauber"
        },
        {
            "word": "quand",
            "translation": "wann"
        },
        {
            "word": "qui",
            "translation": "wer"
        },
        {
            "word": "quoi",
            "translation": "was"
        },
        {
            "word": "rapide",
            "translation": "schnell"
        },
        {
            "word": "regarder",
            "translation": "sehen"
        }
    ]
}